qpdown.py
qpdown-1.0.7.dist-info/LICENSE
qpdown-1.0.7.dist-info/METADATA
qpdown-1.0.7.dist-info/WHEEL
qpdown-1.0.7.dist-info/entry_points.txt
qpdown-1.0.7.dist-info/top_level.txt
qpdown-1.0.7.dist-info/RECORD
