Metadata-Version: 2.2
Name: qpdown
Version: 1.0.7
Summary: a simple m3u8 playlist downloader written in python
Author-email: q16q <q16@q16.dev>
Maintainer-email: q16q <q16@q16.dev>
License: MIT License
Project-URL: Homepage, https://github.com/q16q/qpdown
Project-URL: Issues, https://github.com/q16q/qpdown/issues
Keywords: downloader,m3u8,playlist,playlist-downloader
Classifier: Programming Language :: Python :: 3
Classifier: Operating System :: OS Independent
Requires-Python: >=3.8
License-File: LICENSE
